{
  "fr": {
    "news": {
      "title" : "Nouveau",
      "content" : [
        "Nouvelle prestation : Pose de vernis semi permanent - Promotion 22 euros jusqu'au 15 Juillet !",
        "Arrivée de la marque ONE MINUTE au cabinet - Gommages, huiles et baumes déjà disponible au cabinet !"
      ]
    },
    "media": {
      "type" : "video",
      "video" : {
        "title" : "Un cabinet de tatouage médical à Niort",
        "source" : "https://www.youtube.com/embed/HFgBaR0D8cM"
      },
      "photo" : {
        "items" : [
          {
            "source" : "./../../../medias/accueil/test1.webp",
            "header" : "TEST JSON",
            "text" : "text test json"
          }
        ]
      }
    }
  },
  "en": {
    "news": {
      "title" : "News",
      "content" : [
        "Learn the history of the cabinet in the about part",
        "Found more informations in the contact part"
      ]
    },
    "media": {
      "type" : "video",
      "video" : {
        "title" : "Medical tattoo cabine in Niort",
        "source" : "https://www.youtube.com/embed/HFgBaR0D8cM"
      },
      "photo" : {
        "items" : [
          {
            "source" : "./../../../medias/accueil/test1.webp",
            "header" : "TEST JSON",
            "text" : "text test json"
          }
        ]
      }
    }
  }
}
